LICENSE
MANIFEST.in
README.txt
setup.cfg
setup.py
TracCronPlugin.egg-info/PKG-INFO
TracCronPlugin.egg-info/SOURCES.txt
TracCronPlugin.egg-info/dependency_links.txt
TracCronPlugin.egg-info/entry_points.txt
TracCronPlugin.egg-info/requires.txt
TracCronPlugin.egg-info/top_level.txt
tests/conftest.py
tests/test_auto_postpone_task.py
tests/test_core.py
tests/test_cron_scheduler.py
tests/test_cronconf.py
tests/test_daily_scheduler.py
tests/test_heart_beat_task.py
tests/test_history_task_event.py
tests/test_hourly_scheduler.py
tests/test_memory_history_store.py
tests/test_monthly_scheduler.py
tests/test_notification_email_task_event.py
tests/test_scheduler_type.py
tests/test_sleeping_ticket_reminder_task.py
tests/test_ticker.py
tests/test_ticket_deadline_task.py
tests/test_unreachable_milestone_task.py
tests/test_weekly_scheduler.py
tests/utils.py
traccron/__init__.py
traccron/api.py
traccron/core.py
traccron/history.py
traccron/listener.py
traccron/scheduler.py
traccron/task.py
traccron/templates/cron_admin.html
traccron/templates/cron_history.html
traccron/templates/cron_history.rss
traccron/templates/cron_listener.html
traccron/templates/notify_task_event_template.txt
traccron/templates/notify_ticket_near_deadline.txt
traccron/templates/opened_ticket_for_owner_template.txt
traccron/templates/opened_ticket_for_reporter_template.txt
traccron/templates/orphaned_ticket_template.txt
traccron/templates/sleeping_ticket_template.txt
traccron/templates/unreachable_milestone_template.txt