Metadata-Version: 1.1
Name: TracCronPlugin
Version: 0.3
Summary: Task scheduler plugin for Trac
Home-page: http://trac-hacks.org/wiki/TracCronPlugin
Author: Tetsuya Morimoto
Author-email: tetsuya.morimoto@gmail.com
License: BSD
Keywords: trac cron scheduler plugin
Platform: unix
Platform: linux
Platform: osx
Platform: windows
Classifier: Framework :: Trac
Classifier: Development Status :: 4 - Beta
Classifier: Environment :: Web Environment
Classifier: License :: OSI Approved :: BSD License
Classifier: Intended Audience :: Developers
Classifier: Operating System :: OS Independent
Classifier: Programming Language :: Python
Classifier: Topic :: Software Development
